python_tia/__init__.py
python_tia-0.0.0.dist-info/METADATA
python_tia-0.0.0.dist-info/RECORD
python_tia-0.0.0.dist-info/WHEEL
python_tia-0.0.0.dist-info/top_level.txt
